dollos.py
dolos_jwt-1.0.2.dist-info/licenses/LICENSE.txt
dolos_jwt-1.0.2.dist-info/METADATA
dolos_jwt-1.0.2.dist-info/WHEEL
dolos_jwt-1.0.2.dist-info/entry_points.txt
dolos_jwt-1.0.2.dist-info/top_level.txt
dolos_jwt-1.0.2.dist-info/RECORD
