Metadata-Version: 2.4
Name: dolos-jwt
Version: 1.0.2
Summary: DOLOS: ASI-Driven JWT Neural Analyzer & Forgery Engine
Author-email: Djin <djin@blacktracelabs.com>
License: MIT
Project-URL: Homepage, https://blacktracelabs.com
Keywords: jwt,bugbounty,security,asi,hacking,jwe,jws
Classifier: Development Status :: 4 - Beta
Classifier: Intended Audience :: Information Technology
Classifier: Topic :: Security
Classifier: License :: OSI Approved :: MIT License
Classifier: Programming Language :: Python :: 3.13
Requires-Python: >=3.10
License-File: LICENSE.txt
Requires-Dist: authlib
Requires-Dist: rich
Requires-Dist: cryptography
Dynamic: license-file
